{
	"$schema": "https://schemas.wp.org/trunk/block.json",
	"apiVersion": 3,
	"name": "create-block/download-go-further",
	"version": "0.1.0",
	"title": "Pour aller plus loin",
	"category": "widgets",
	"description": "Block pour aller plus loin, téléchargement de fichiers",
	"attributes": {
		"title": {
			"type": "string",
			"default": "Titre"
		}
	},
	"example": {},
	"supports": {
		"html": false
	},
	"textdomain": "download-go-further",
	"editorScript": "file:./index.js",
	"editorStyle": "file:./index.css",
	"style": "file:./style-index.css",
	"viewScript": "file:./view.js"
}
